pycounts_njv/__init__.py
pycounts_njv/plotting.py
pycounts_njv/pycounts_njv.py
pycounts_njv-0.1.0.dist-info/LICENSE
pycounts_njv-0.1.0.dist-info/WHEEL
pycounts_njv-0.1.0.dist-info/METADATA
pycounts_njv-0.1.0.dist-info/RECORD
